dwiprep/__init__.py
dwiprep/cli/__init__.py
dwiprep/cli/cli.py
dwiprep/cli/configuration.py
dwiprep/cli/utils/__init__.py
dwiprep/cli/utils/parse_subject.py
dwiprep/preprocessing/__init__.py
dwiprep/preprocessing/messages.py
dwiprep/preprocessing/preprocess.py
dwiprep/preprocessing/utils/__init__.py
dwiprep/preprocessing/utils/conversions.py
dwiprep/preprocessing/utils/fetch_files.py
dwiprep/preprocessing/utils/mrtrix_functions.py
dwiprep/registrations/__init__.py
dwiprep/registrations/messages.py
dwiprep/registrations/registrations.py
dwiprep/registrations/utils/__init__.py
dwiprep/registrations/utils/fsl_functions.py
dwiprep/registrations/utils/matlab_functions.py
dwiprep-0.1.5.dist-info/LICENSE
dwiprep-0.1.5.dist-info/METADATA
dwiprep-0.1.5.dist-info/WHEEL
dwiprep-0.1.5.dist-info/top_level.txt
dwiprep-0.1.5.dist-info/RECORD
