Metadata-Version: 2.1
Name: dwiprep
Version: 0.1.5
Summary: DWIprep is a robust and easy-to-use preprocessing pipeline for diffusion-weighted imaging of various acquisitions.
Home-page: https://github.com/GalBenZvi/dwiprep
Author: Gal Ben-Zvi
Author-email: benzvigal@gmail.com
License: MIT
Project-URL: Source, https://github.com/GalBenZvi/dwiprep
Project-URL: Bug Reports, https://github.com/GalBenZvi/dwiprep/issues/
Keywords: mri,dwi,python,neuroimaging
Platform: UNKNOWN
Classifier: Development Status :: 5 - Production/Stable
Classifier: Intended Audience :: Science/Research
Classifier: Intended Audience :: Healthcare Industry
Classifier: License :: OSI Approved :: MIT License
Classifier: Operating System :: OS Independent
Classifier: Programming Language :: Python :: 3
Classifier: Programming Language :: Python :: 3.6
Classifier: Programming Language :: Python :: 3.7
Classifier: Programming Language :: Python :: 3.8
Classifier: Programming Language :: Python :: 3.9
Classifier: Programming Language :: Python :: 3 :: Only
Requires-Python: <4,>=3.6
License-File: LICENSE
Requires-Dist: pydicom (~=2.1.2)
Requires-Dist: numpy ; python_version == "3.6"
Requires-Dist: numpy (~=1.21) ; python_version > "3.6"
Provides-Extra: all
Requires-Dist: black (==21.5b1) ; extra == 'all'
Requires-Dist: build ; extra == 'all'
Requires-Dist: nibabel (~=1.6) ; extra == 'all'
Requires-Dist: pybids (~=0.12) ; extra == 'all'
Requires-Dist: termcolor (~=1.1) ; extra == 'all'
Requires-Dist: coverage[toml] (~=5.5) ; extra == 'all'
Requires-Dist: coverage-badge (~=1.0) ; extra == 'all'
Requires-Dist: doc8 (~=0.8) ; extra == 'all'
Requires-Dist: flake8 (~=3.7) ; extra == 'all'
Requires-Dist: ipython ; extra == 'all'
Requires-Dist: isort (~=5.8) ; extra == 'all'
Requires-Dist: jinja2 (~=3.0) ; extra == 'all'
Requires-Dist: pandas (~=1.3) ; extra == 'all'
Requires-Dist: pytest (~=6.2) ; extra == 'all'
Requires-Dist: sphinx (~=4.0) ; extra == 'all'
Requires-Dist: sphinx-rtd-theme (~=0.5) ; extra == 'all'
Requires-Dist: tox (~=3.23) ; extra == 'all'
Requires-Dist: twine ; extra == 'all'
Requires-Dist: python-magic (~=0.4) ; (platform_system != "Windows") and extra == 'all'
Requires-Dist: pickle5 (~=0.0) ; (python_version <= "3.7") and extra == 'all'
Provides-Extra: dev
Requires-Dist: black (==21.5b1) ; extra == 'dev'
Requires-Dist: coverage[toml] (~=5.5) ; extra == 'dev'
Requires-Dist: doc8 (~=0.8) ; extra == 'dev'
Requires-Dist: flake8 (~=3.7) ; extra == 'dev'
Requires-Dist: ipython ; extra == 'dev'
Requires-Dist: isort (~=5.8) ; extra == 'dev'
Requires-Dist: pytest (~=6.2) ; extra == 'dev'
Requires-Dist: sphinx (~=4.0) ; extra == 'dev'
Requires-Dist: sphinx-rtd-theme (~=0.5) ; extra == 'dev'
Requires-Dist: tox (~=3.23) ; extra == 'dev'
Requires-Dist: python-magic (~=0.4) ; (platform_system != "Windows") and extra == 'dev'
Provides-Extra: dist
Requires-Dist: build ; extra == 'dist'
Requires-Dist: twine ; extra == 'dist'
Provides-Extra: docs
Requires-Dist: sphinx (~=4.0) ; extra == 'docs'
Requires-Dist: sphinx-rtd-theme (~=0.5) ; extra == 'docs'
Provides-Extra: magic
Requires-Dist: python-magic (~=0.4) ; (platform_system != "Windows") and extra == 'magic'
Provides-Extra: pandas
Requires-Dist: jinja2 ; extra == 'pandas'
Requires-Dist: pandas ; extra == 'pandas'
Provides-Extra: test
Requires-Dist: coverage[toml] (~=5.5) ; extra == 'test'
Requires-Dist: pytest (~=6.2) ; extra == 'test'
Requires-Dist: tox (~=3.23) ; extra == 'test'
Requires-Dist: python-magic (~=0.4) ; (platform_system != "Windows") and extra == 'test'
Requires-Dist: pickle5 (~=0.0) ; (python_version <= "3.7") and extra == 'test'
